gdromops/__init__.py
gdromops/cache.py
gdromops/config.py
gdromops/engine.py
gdromops/loader.py
gdromops/parser.py
gdromops-0.1.0.dist-info/licenses/LICENSE
gdromops-0.1.0.dist-info/METADATA
gdromops-0.1.0.dist-info/WHEEL
gdromops-0.1.0.dist-info/top_level.txt
gdromops-0.1.0.dist-info/RECORD
