Metadata-Version: 2.4
Name: gdromops
Version: 0.1.0
Summary: On-demand reservoir operation rules loader and simulator (GDROM)
Author: Zihan Zheng
License: MIT
Project-URL: Homepage, https://github.com/ZihanZheng2000/gdromops
Requires-Python: >=3.9
License-File: LICENSE
Requires-Dist: pandas>=1.5
Requires-Dist: requests>=2.31
Dynamic: license-file
